[
  {
    "pair_id": "PAIR-0237",
    "hazard_photo": "알앤투동탄_2022/SAFEG-RT-D-2022-U-0046.jpg",
    "measure_photo": "알앤투동탄_2022/SAFEG-RT-D-2022-U-0047.jpg"
  },
  {
    "pair_id": "PAIR-0238",
    "hazard_photo": "알앤투동탄_2022/SAFEG-RT-D-2022-U-0048.jpg",
    "measure_photo": "알앤투동탄_2022/SAFEG-RT-D-2022-U-0049.jpg"
  },
  {
    "pair_id": "PAIR-0239",
    "hazard_photo": "알앤투동탄_2022/SAFEG-RT-D-2022-U-0050.jpg",
    "measure_photo": "알앤투동탄_2022/SAFEG-RT-D-2022-U-0051.jpg"
  },
  {
    "pair_id": "PAIR-0240",
    "hazard_photo": "알앤투동탄_2022/SAFEG-RT-D-2022-U-0052.jpg",
    "measure_photo": "알앤투동탄_2022/SAFEG-RT-D-2022-U-0053.jpg"
  },
  {
    "pair_id": "PAIR-0241",
    "hazard_photo": "알앤투동탄_2022/SAFEG-RT-D-2022-U-0054.jpg",
    "measure_photo": "알앤투동탄_2022/SAFEG-RT-D-2022-U-0055.jpg"
  },
  {
    "pair_id": "PAIR-0242",
    "hazard_photo": "알앤투동탄_2022/SAFEG-RT-D-2022-U-0056.jpg",
    "measure_photo": "알앤투동탄_2022/SAFEG-RT-D-2022-U-0057.jpg"
  },
  {
    "pair_id": "PAIR-0243",
    "hazard_photo": "알앤투동탄_2022/SAFEG-RT-D-2022-U-0058.jpg",
    "measure_photo": "알앤투동탄_2022/SAFEG-RT-D-2022-U-0059.jpg"
  },
  {
    "pair_id": "PAIR-0244",
    "hazard_photo": "알앤투동탄_2022/SAFEG-RT-D-2022-U-0060.jpg",
    "measure_photo": "알앤투동탄_2022/SAFEG-RT-D-2022-U-0061.jpg"
  },
  {
    "pair_id": "PAIR-0245",
    "hazard_photo": "알앤투동탄_2022/SAFEG-RT-D-2022-U-0062.jpg",
    "measure_photo": "알앤투동탄_2022/SAFEG-RT-D-2022-U-0063.jpg"
  },
  {
    "pair_id": "PAIR-0246",
    "hazard_photo": "알앤투동탄_2022/SAFEG-RT-D-2022-U-0064.jpg",
    "measure_photo": "알앤투동탄_2022/SAFEG-RT-D-2022-U-0065.jpg"
  },
  {
    "pair_id": "PAIR-0247",
    "hazard_photo": "알앤투동탄_2022/SAFEG-RT-D-2022-U-0066.jpg",
    "measure_photo": "알앤투동탄_2022/SAFEG-RT-D-2022-U-0067.jpg"
  },
  {
    "pair_id": "PAIR-0248",
    "hazard_photo": "알앤투동탄_2022/SAFEG-RT-D-2022-U-0068.jpg",
    "measure_photo": "알앤투동탄_2022/SAFEG-RT-D-2022-U-0069.jpg"
  },
  {
    "pair_id": "PAIR-0249",
    "hazard_photo": "알앤투동탄_2022/SAFEG-RT-D-2022-U-0070.jpg",
    "measure_photo": "알앤투동탄_2022/SAFEG-RT-D-2022-U-0071.jpg"
  },
  {
    "pair_id": "PAIR-0250",
    "hazard_photo": "알앤투동탄_2022/SAFEG-RT-D-2022-U-0072.jpg",
    "measure_photo": "알앤투동탄_2022/SAFEG-RT-D-2022-U-0073.jpg"
  },
  {
    "pair_id": "PAIR-0251",
    "hazard_photo": "알앤투동탄_2022/SAFEG-RT-D-2022-U-0074.jpg",
    "measure_photo": "알앤투동탄_2022/SAFEG-RT-D-2022-U-0075.jpg"
  },
  {
    "pair_id": "PAIR-0252",
    "hazard_photo": "알앤투동탄_2022/SAFEG-RT-D-2022-U-0076.jpg",
    "measure_photo": "알앤투동탄_2022/SAFEG-RT-D-2022-U-0077.jpg"
  },
  {
    "pair_id": "PAIR-0253",
    "hazard_photo": "알앤투동탄_2022/SAFEG-RT-D-2022-U-0078.jpg",
    "measure_photo": "알앤투동탄_2022/SAFEG-RT-D-2022-U-0079.jpg"
  },
  {
    "pair_id": "PAIR-0254",
    "hazard_photo": "알앤투동탄_2022/SAFEG-RT-D-2022-U-0080.jpg",
    "measure_photo": "알앤투동탄_2022/SAFEG-RT-D-2022-U-0081.jpg"
  },
  {
    "pair_id": "PAIR-0255",
    "hazard_photo": "알앤투동탄_2022/SAFEG-RT-D-2022-U-0082.jpg",
    "measure_photo": "알앤투동탄_2022/SAFEG-RT-D-2022-U-0083.jpg"
  },
  {
    "pair_id": "PAIR-0256",
    "hazard_photo": "알앤투동탄_2022/SAFEG-RT-D-2022-U-0084.jpg",
    "measure_photo": "알앤투동탄_2022/SAFEG-RT-D-2022-U-0085.jpg"
  },
  {
    "pair_id": "PAIR-0257",
    "hazard_photo": "알앤투동탄_2022/SAFEG-RT-D-2022-U-0086.jpg",
    "measure_photo": "알앤투동탄_2022/SAFEG-RT-D-2022-U-0087.jpg"
  },
  {
    "pair_id": "PAIR-0258",
    "hazard_photo": "알앤투동탄_2022/SAFEG-RT-D-2022-U-0088.jpg",
    "measure_photo": "알앤투동탄_2022/SAFEG-RT-D-2022-U-0089.jpg"
  },
  {
    "pair_id": "PAIR-0259",
    "hazard_photo": "알앤투동탄_2022/SAFEG-RT-D-2022-U-0090.jpg",
    "measure_photo": "알앤투동탄_2022/SAFEG-RT-D-2022-U-0091.jpg"
  }
]